setup.cfg
setup.py
tc_shortener/__init__.py
tc_shortener/shortener.py
tc_shortener.egg-info/PKG-INFO
tc_shortener.egg-info/SOURCES.txt
tc_shortener.egg-info/dependency_links.txt
tc_shortener.egg-info/not-zip-safe
tc_shortener.egg-info/requires.txt
tc_shortener.egg-info/top_level.txt
tc_shortener/generators/__init__.py
tc_shortener/generators/sha256_generator.py
tc_shortener/generators/short_generator.py
tc_shortener/handlers/__init__.py
tc_shortener/handlers/shortener.py
tc_shortener/storages/__init__.py
tc_shortener/storages/redis_storage.py
vows/__init__.py
vows/generators/__init__.py
vows/generators/sha256_generator_vows.py
vows/generators/short_generator_vows.py