Metadata-Version: 1.1
Name: tc-shortener
Version: 0.2.2
Summary: URL Shortener
Home-page: http://github.com/thumbor-community/shortener
Author: Thumbor Community
Author-email: UNKNOWN
License: MIT
Platform: any
Classifier: Development Status :: 4 - Beta
Classifier: Intended Audience :: Developers
Classifier: License :: OSI Approved :: MIT License
Classifier: Operating System :: OS Independent
Classifier: Programming Language :: Python
Classifier: Topic :: Software Development :: Libraries :: Python Modules
